<?xml version="1.0" encoding="UTF-8"?>
<!DOCTYPE html PUBLIC "-//W3C//DTD XHTML 1.0 Transitional//EN" "http://www.w3.org/TR/xhtml1/DTD/xhtml1-transitional.dtd">
<root>
<body><page page_number="1" transcanno_page_id="966"><paragraph class="medium-paragraph" tagcode="1551632683392"><div>Eigentlich wollten Cleo und Markus nur</div><div>einen kleinen Waldspaziergang machen , doch</div><div>das Geplante nahm ein unerwartetes Ende.</div><div>Es war ein <orth_error_id12 class="medium-orth_error_id12" orth_error_target="gewöhnlicher" tagcode="1551630162297">gewohnlicher</orth_error_id12> Freitagabend als</div><div>die <orth_error_id12 class="medium-orth_error_id12" orth_error_target="beiden" tagcode="1551630196722">Beiden</orth_error_id12> den Wald betraten. Mit Taschenlampen</div><div>stapften sie langsam den Waldweg entlang.</div><div>Vielleicht hatten sie die Entscheidung im gruseligen</div><div>Wald einen Spaziergang zu machen doch ein</div><div><orth_error_id12 class="medium-orth_error_id12" orth_error_target="bisschen" tagcode="1551630330906">bischen</orth_error_id12> unterschätzt. Beiden <orth_error_id12 class="medium-orth_error_id12" orth_error_target="schlotterten" tagcode="1551632630179">Schlotterten</orth_error_id12> bereits</div><div>die Knie aber umkehren kam jetzt nicht</div><div>mehr <orth_error_id12 class="medium-orth_error_id12" orth_error_target="in Frage" tagcode="1551631297482">infrage</orth_error_id12>. Der Waldweg endete <tran_word_correction_id25 class="medium-tran_word_correction_id25" tagcode="1551631321538" tran_correction_original="a*">an</tran_word_correction_id25></div><div>einer <tran_ambiguous_id3 class="medium-tran_ambiguous_id3" tagcode="1551632588948" tran_alternative_1="schmalen" tran_alternative_2="Schmalen">schmalen</tran_ambiguous_id3> Lichtung, durch die ein Bächlein</div><div>floss. Ihre Angst nahm zu als plötzlich</div><div>auch noch Cleos Taschenlampe ausging .</div><div>Auf einmal hallten etliche Schreie durch</div><div>das Waldstück auf sie zu. „ Was war das?" ,</div><div>fragte Cleo <orth_error_id12 class="medium-orth_error_id12" orth_error_target="ängstlich" tagcode="1551631564067">angstlich</orth_error_id12>. I-ich weiß es nicht ,</div><div><orth_error_id12 class="medium-orth_error_id12" orth_error_target="stotterte" tagcode="1551631627004">Stotterte</orth_error_id12> Markus zurück. Markus richtete</div><div><orth_error_id12 class="medium-orth_error_id12" orth_error_target="seine" tagcode="1551632683391">Seine</orth_error_id12> Taschenlampe auf das Waldstück</div><div>vor ihnen. Plötzlich raschelte etwas im</div><div>Gebüsch. Als Cleo sich langsam an</div><div>das Gebüsch <orth_error_id12 class="medium-orth_error_id12" orth_error_target="rausschleichen" tagcode="1551631859022">rauschleichen</orth_error_id12> wollte ,</div></paragraph></page><page page_number="2" transcanno_page_id="967"><paragraph class="medium-paragraph" tagcode="1551632683393"><div>verstummten plötzlich die Schreie . Zu ihrer</div><div><orth_error_id12 class="medium-orth_error_id12" orth_error_target="Überraschung" tagcode="1551631937256">überraschung</orth_error_id12> war das Gebüsch leer. Sie</div><div>nutzten den Augenblick der Stille und</div><div>rannten so schnell sie konnten aus dem</div><div>Wald. Seit jeher ist deshalb der Wald</div><div>auch als Wald der <orth_error_id12 class="medium-orth_error_id12" orth_error_target="schreienden" tagcode="1551632053277">Schreienden</orth_error_id12> Bäume</div><div>bekannt.</div></paragraph></page></body>
</root>