<?xml version="1.0" encoding="UTF-8"?>
<kolipsi_document xmlns="http://www.eurac.edu/kolipsi"
                  xmlns:xsi="http://www.w3.org/2001/XMLSchema-instance"
                  xmlns:xs="http://www.w3.org/2001/XMLSchema"
                  xmlns:ns="http://www.eurac.edu/kolipsi"
                  xsi:schemaLocation="http://www.eurac.edu/kolipsi file:kolipsi.xsd">
  <transcriber>Yella</transcriber>

  <author_id>M0094</author_id>

  <exam_type>Kolipsi</exam_type>

  <text_language>Deutsch</text_language>

  <body>
    

      <exercise number="2" xml:space="preserve"><greeting>Hallo <entity>Jenny</entity></greeting>,<par/>auch wenn wir uns schon seit unserem letzte<ambiguous>
        <alternative>m</alternative>

        <alternative>n</alternative>
      </ambiguous> Brief nicht mehr gesehen haben, oder wahrscheinlich genau deshalb <correction>
        <deletion><unreadable/></deletion>
      </correction> freue ich mich schon riesig auf unseren gemeinsamen Urlaub im Sommer. Aber ein Problem gibt es noch. Fahren wir ans Meer oder in die Berge? Genießen wir am Strand die Sonne oder gehen wir lieber in schönen Tälern wandern? Oder sollen wir lieber schwimmen gehen, anstatt mal etwas <error>
        <errorType/>

        <originalForm>neues</originalForm>

        <targetForm>Neues</targetForm>
      </error> auszuprobieren und vielleicht einmal klettern gehen? Ich kann mich immer noch nicht entscheiden. Ist es schöner die Abende am Wasser oder in einer schönen Berghütte ausklingen zu lassen. Was wäre dir <error>
        <errorType/>

        <originalForm>den</originalForm>

        <targetForm>denn</targetForm>
      </error> lieber? Also, ich glau<over>b</over>e ich könnte mich <gap>_</gap> beid<over>e</over>m anfreunden. Aber inzwischen glaube ich es wäre viel schöner, sich, <emphasis>so richtig</emphasis> zu erholen. Also am besten gar nichts tun, außer braun werden &amp; am Strand liegen. Mal so richtig ab<hyphen>-</hyphen>schalten und alles mal so richtig verdrängen. Den ganzen öden Alltag. Letztes Jahr war i<overwrite>
        <under>s</under>

        <over>c</over>
      </overwrite>h schon einmal am Meer. In <entity>Südfrankreich</entity>. Und ich kann nur sagen: <error>
        <errorType/>

        <originalForm>es</originalForm>

        <targetForm>Es</targetForm>
      </error> lohnt sich wirklich. Nicht nur die Leute sind supernett, auch die Gegend ist wunderschön. Wir könnten ja trotzdem wandern oder einfach nur gemütlich am Strand spazieren gehen. Sag mir schnell <error>
        <errorType/>

        <originalForm>bescheid</originalForm>

        <targetForm>Bescheid</targetForm>
      </error>, wenn du dich entschieden hast. Dann können wir so schnell wie möglich den Urlaub buchen.<par/><closing>Liebe Grüße <entity>XY</entity></closing> </exercise>
  </body>
</kolipsi_document>