<?xml version="1.0" encoding="utf-8"?>
<kolipsi_II_document xsi:schemaLocation="http://www.eurac.edu/kolipsi_II kolipsi_II.xsd"
                     xmlns="http://www.eurac.edu/kolipsi_II"
                     xmlns:xsi="http://www.w3.org/2001/XMLSchema-instance"
                     xmlns:xs="http://www.w3.org/2001/XMLSchema"
                     xmlns:ns="http://www.eurac.edu/kolipsi_II">
  <transcriber>Anna</transcriber>

  <author_id>I03_BUZ14MAR</author_id>

  <exam_type>Kolipsi II</exam_type>

  <text_language>Deutsch</text_language>

  <body>
    <exercise number="1" xml:space="preserve"><greeting>Lieber Lukas,</greeting><par />ich schreibe dir weil ich die Geschichte von Maria dir erzählen möchte. Meine Freundin Maria war letzte Woche einkaufen. Sie kaufte Obst und <correction>
        <deletion>Gm<unreadable /></deletion>
      </correction> Gemüse und dann ging sie im <foreign_word
        foreign_language="Italiano">Supermarket</foreign_word>. Dort gab es ein Problem an der Kasse <correction>
        <deletion>weil</deletion>
      </correction>, Maria hat bezahlen aber die <correction>
        <deletion>Kom<unreadable />es</deletion>
      </correction> <foreign_word foreign_language="Italiano"><error>
          <errorType />

          <originalForm>Kommesse</originalForm>

          <targetForm>Commessa</targetForm>
        </error></foreign_word> sieht das Obst und die Gemüse und sie glaubt dass Maria es <correction>
        <deletion>gekländet</deletion>

        <insertion><error>
            <errorType />

            <originalForm>gestolen</originalForm>

            <targetForm>gestohlen</targetForm>
          </error></insertion>
      </correction> hat. Maria war nicht <error>
        <errorType />

        <originalForm>fröh</originalForm>

        <targetForm>froh</targetForm>
      </error> weil sie eine gute Mensch ist. Die <foreign_word
        foreign_language="Other"><error>
          <errorType />

          <originalForm>Kommesse</originalForm>

          <targetForm>Commessa</targetForm>
        </error></foreign_word> rufte also die Polizei. <correction>
        <deletion>Wen</deletion>
      </correction> Wann sie kommte, <correction>
        <deletion>Mar<unreadable /></deletion>
      </correction> nehmten Maria um zu sprechen. Sie sagte dass sie nie gemacht habe, dass sie das <error>
        <errorType />

        <originalForm>Obs</originalForm>

        <targetForm>Obst</targetForm>
      </error> und die Gemüse in einem Obst- und Gemüeladen gekaufen habe. Aber die Polizei glaubt dass sie es <error>
        <errorType />

        <originalForm>gestolen</originalForm>

        <targetForm>gestohlen</targetForm>
      </error> hat. Also Maria sagte ihnen dass sie bei dem Obst- und Gemüseladen ging könnten. <correction>
        <deletion>um Sie die <unreadable /></deletion>
      </correction> Die Polizei <correction>
        <deletion>geht</deletion>
      </correction> ging und seh dass Maria Recht hatte. Jetzt konnte Maria nach Hause gehen.</exercise>

    <exercise number="2" xml:space="preserve"><greeting>Sehr <correction>
          <deletion>geehert</deletion>
        </correction> <error>
          <errorType />

          <originalForm>gehert</originalForm>

          <targetForm>geehert</targetForm>
        </error> Paul,</greeting><par />ich habe deine <error>
        <errorType />

        <originalForm>email</originalForm>

        <targetForm>E-Mail</targetForm>
      </error> in der Rubrik "Persönliche Briefe" der Zeitung "Junge Woche" gelesen. Ich schreibe dir weil ich dich helfen möchte und ich <correction>
        <deletion>gebe</deletion>
      </correction> probiere <correction>
        <deletion><unreadable /><correction>
            <insertion><unreadable /></insertion>
          </correction></deletion>
      </correction> dir eine Lösung geben. Du bist in eine <error>
        <errorType />

        <originalForm>schlachte</originalForm>

        <targetForm>schlechte</targetForm>
      </error> Situation aber du <error>
        <errorType />

        <originalForm>kontest</originalForm>

        <targetForm>konntest</targetForm>
      </error> auskommen. Ich denke <error>
        <errorType />

        <originalForm>das</originalForm>

        <targetForm>dass</targetForm>
      </error> virtuelle Freundschaften nicht gut sind. Sie sind wie eine Droge weil man immer auf Internet und auf die Social Networkt bleiben muss. Man sollte <error>
        <errorType />

        <originalForm>aus gehen</originalForm>

        <targetForm>ausgehen</targetForm>
      </error> und <correction>
        <deletion>d</deletion>
      </correction> mit der Natur leben und nicht mit dem Handy oder dem Computer, man <correction>
        <deletion>muss</deletion>
      </correction> sollte <error>
        <errorType />

        <originalForm>Frei</originalForm>

        <targetForm>frei</targetForm>
      </error> sein. Einen Rat kann einen anderen <error>
        <errorType />

        <originalForm>Sim</originalForm>

        <targetForm>SIM</targetForm>
      </error> nehmen sein. Die virtuelle Freundschaften sind nicht Freundschaften weil du nicht die Leute in Realität sieht. Wenn du auf Internet geht, du vergisst dein Zeit. Du <correction>
        <deletion>mu</deletion>
      </correction> muss aus <correction>
        <deletion>ge</deletion>
      </correction> mit deinem Freunden gehen aber die <correction>
        <deletion>Rea</deletion>
      </correction> reale Freunden und nicht die virtuelle. Also <correction>
        <deletion>nimm</deletion>
      </correction> nimmt dein Handy und brache es.<par /><correction>
        <deletion>Li</deletion>
      </correction> <closing>Viele Gruße,</closing><par /><correction>
        <deletion>Marco</deletion>
      </correction> Bred <correction>
        <deletion><unreadable /></deletion>
      </correction> Roger </exercise>
  </body>
</kolipsi_II_document>
