<?xml version="1.0" encoding="utf-8"?>
<kolipsi_II_document xsi:schemaLocation="http://www.eurac.edu/kolipsi_II kolipsi_II.xsd"
                     xmlns="http://www.eurac.edu/kolipsi_II"
                     xmlns:xsi="http://www.w3.org/2001/XMLSchema-instance"
                     xmlns:xs="http://www.w3.org/2001/XMLSchema"
                     xmlns:ns="http://www.eurac.edu/kolipsi_II">
  <transcriber>Anna</transcriber>

  <author_id>I24_CAP03ELE</author_id>

  <exam_type>Kolipsi II</exam_type>

  <text_language>Deutsch</text_language>

  <body>
    <exercise number="1" xml:space="preserve"><greeting>Hallo Giulia,</greeting><par /><error>
        <errorType />

        <originalForm>Ich</originalForm>

        <targetForm>ich</targetForm>
      </error> bin Federica. Ich bin deine beste Freundin.<par />Jetzt erzähle ich dich eine lustige Geschichte. Maria (meine Freundin von Schule) ist in einen <error>
        <errorType />

        <originalForm>Supermakt</originalForm>

        <targetForm>Supermarkt</targetForm>
      </error> gegangen. Sie hat Gemüse und Obst gekauft. Danach <correction>
        <deletion>ist</deletion>
      </correction> hat sie den Kassenzettel auf der Tisch vergessen. Dann ist sie in einen andere <error>
        <errorType />

        <originalForm>Supermakt</originalForm>

        <targetForm>Supermarkt</targetForm>
      </error> gegangen. Sie hat viele Dinge gekauft (<foreign_word
        foreign_language="English">Milk</foreign_word>, Brot, Pizza <correction>
        <deletion><unreadable /></deletion>
      </correction>, Coca Cola, <error>
        <errorType />

        <originalForm>Cips</originalForm>

        <targetForm>Chips</targetForm>
      </error>...). Sie m<correction>
        <deletion>ü</deletion>

        <insertion>u</insertion>
      </correction>ss eine Party organisieren. Sie ist nach die Kasse gegangen. Dort <correction>
        <deletion>haben <unreadable /></deletion>
      </correction> hat sie einen kleinen Problem. Der Kassenperson hat mit Maria <error>
        <errorType />

        <originalForm>geschtreit</originalForm>

        <targetForm>gestreit</targetForm>
      </error><correction>
        <insertion>.</insertion>

        <deletion>,weil sie</deletion>
      </correction> Der Kassenperson <correction>
        <deletion>denkt</deletion>
      </correction> hat gedacht, dass Maria will nicht das Obst und die Gemüse kaufen. Aber sie hat <error>
        <errorType />

        <originalForm>dises</originalForm>

        <targetForm>dieses</targetForm>
      </error> Essen <correction>
        <deletion>in</deletion>
      </correction> beim <error>
        <errorType />

        <originalForm>Obsthandler</originalForm>

        <targetForm>Obsthändler</targetForm>
      </error> gekauft. Sie hat dem Kassenzettel vergessen.<par />Danach <correction>
        <deletion>i</deletion>
      </correction> hat sie mit dem Chef <correction>
        <deletion>gesch<unreadable /></deletion>
      </correction> <error>
        <errorType />

        <originalForm>gespochen</originalForm>

        <targetForm>gesprochen</targetForm>
      </error>. Sie hat <correction>
        <deletion>die Geschi</deletion>
      </correction> dieses Geschichte erzählt. Dann hat sie keinen Probleme.<par />Findest du diese <error>
        <errorType />

        <originalForm>geschichte</originalForm>

        <targetForm>Geschichte</targetForm>
      </error> lustig? Heute Maria war nicht sehr glücklich!<par /><correction>
        <deletion>Ich</deletion>
      </correction> <closing>Ich warte auf dich!<par />Viele Grüße</closing><par />Federica. </exercise>

    <exercise number="2" xml:space="preserve"><greeting>Hallo Paul,</greeting><par /><error>
        <errorType />

        <originalForm>Ich</originalForm>

        <targetForm>ich</targetForm>
      </error> bin Federica und ich habe deine persönliche Briefe gelesen.<par />Auch meinen <correction>
        <deletion>ich</deletion>
      </correction> Bruder hat diese Probleme. Er hat auch die Nummern aller Personen aus seinem Handy gelöscht.<par />Ich denk<correction>
        <deletion>t</deletion>

        <insertion>e</insertion>
      </correction>, dass du warten müssen. Ich denke auch, dass du neue Freundschaften <correction>
        <deletion>man</deletion>
      </correction> machen muss!<par />Was denkst über virtuelle Freundschaften haben? Ich denke, dass manchmal sind diese Freundschaften richtig sind. Ich habe auch einen <correction>
        <deletion>Fre</deletion>
      </correction> <error>
        <errorType />

        <originalForm>Internet-Freund</originalForm>

        <targetForm>Internetfreund</targetForm>
      </error>. Was denkst du über die Verwendung des Internet? Internet ist einen schöne <error>
        <errorType />

        <originalForm>Komunikationsmittel</originalForm>

        <targetForm>Kommunikationsmittel</targetForm>
      </error>? Hast du <correction>
        <deletion>f</deletion>
      </correction> Freunden in der Schule? Ich denke, dass sie richtige Freunden sind. Maria ist meine beste Freundin. Sie ist wie meinen Schwester. Was denkst du über die <error>
        <errorType />

        <originalForm>Mädchen-Buben Freundschaft</originalForm>

        <targetForm>Mädchen-Buben-Freundschaft</targetForm>
      </error>? Ist sie richtig? Ich denke man kann <correction>
        <deletion>eine</deletion>
      </correction> die schönste Freundschaft <correction>
        <deletion><unreadable /></deletion>
      </correction> haben. <correction>
        <deletion>Mein<unreadable /> best<unreadable /> Fre</deletion>
      </correction> Ich habe er in Internet gefunden. Welche ist deine Erfahrung im Internet? Hast du richtige Freunden gefindet?<par /><closing>Ich warte auf deine Antwort!<par />Viele Grüße,</closing><par />Federica<par />PS "meine e-mail ist: federica.federica@hotmail.com"</exercise>
  </body>
</kolipsi_II_document>
