<?xml version="1.0" encoding="utf-8"?>
<kolipsi_document xsi:schemaLocation="http://www.eurac.edu/kolipsi file:kolipsi.xsd"
                  xmlns="http://www.eurac.edu/kolipsi"
                  xmlns:xsi="http://www.w3.org/2001/XMLSchema-instance"
                  xmlns:xs="http://www.w3.org/2001/XMLSchema"
                  xmlns:ns="http://www.eurac.edu/kolipsi">
  <transcriber>Yella</transcriber>

  <author_id>M0043</author_id>

  <exam_type>Kolipsi</exam_type>

  <text_language>Deutsch</text_language>

  <body>
    <exercise number="1" xml:space="preserve"><greeting>Hey <entity>Steffi</entity></greeting>,<par />wie geht's dir, alles gut?<par />Du wirst nicht glauben was <entity>Maria</entity> letzte Woche passiert ist! Sie ist <correction>
        <deletion>eine vermeintliche Laden</deletion>
      </correction> neuerdings eine Ladendiebin. Die gute sozial<correction>
        <deletion>e</deletion>
      </correction> <error>
        <errorType />

        <originalForm>angagierte</originalForm>

        <targetForm>engagierte</targetForm>
      </error> <entity>Maria</entity> wird kriminell! Aber natürlich war dies nur der Schein, <correction>
        <deletion>ein</deletion>
      </correction> eine <overwrite>
        <under>k</under>

        <over>K</over>
      </overwrite>opplung schlechter Zufälle . . . . <entity>Maria</entity> hatte uns alle ja zum <correction>
        <deletion><unreadable /></deletion>
      </correction> Dinner eingeladen, dafür musste sie einige Einkäufe tätigen. Du kennst <correction>
        <deletion>ja</deletion>
      </correction> <entity>Maria</entity> - <correction>
        <deletion>unseren</deletion>
      </correction> sie ist ein Biofreak, also kauft sie als <error>
        <errorType />

        <originalForm>erstes</originalForm>

        <targetForm>Erstes</targetForm>
      </error> im Gemüseladen ein. <correction>
        <deletion>Im Kopf schon</deletion>
      </correction> Völlig vertieft in ihre weiteren Planungen ist sie so nachlässig und vergisst den Kassenbon auf <gap>_</gap> Theke und <error>
        <errorType />

        <originalForm>maschiert</originalForm>

        <targetForm>marschiert</targetForm>
      </error> völlig <error>
        <errorType />

        <originalForm>selbst verständlich</originalForm>

        <targetForm>selbstverständlich</targetForm>
      </error>, mit ihren Einkäufen sichtbar in der Tasche verstaut in den Supermarkt. Sie <sic>läd</sic> ihren Einkaufswagen voll und stellt sich an der Kasse<correction>
        <deletion>n</deletion>
      </correction> an. Natürlich <error>
        <errorType />

        <originalForm>immernoch</originalForm>

        <targetForm>immer noch</targetForm>
      </error> mit dem <correction>
        <deletion>ein</deletion>
      </correction> gefüllten Einkaufs<hyphen>-</hyphen>korb unter dem Arm, dessen Inhalt sie natürlich nicht auf das Laufband legt. Da wurde die Verkäuferin direkt stutzig, wollte wissen was mit dem Rest ist. <entity>Maria</entity> erklärte ihr ganz unschul<hyphen>-</hyphen>dig die Situation: <error>
        <errorType />

        <originalForm>das</originalForm>

        <targetForm>dass</targetForm>
      </error> sie gerade eben im Gemüseladen gewesen sei, aber auch noch andere Produkte kaufen musste. <correction>
        <deletion>Doch</deletion>
      </correction> Sie könne dies sofort durch den Bon beweisen. Nachdem die ganze Tasche, die Hosen <correction>
        <deletion>Taschen un</deletion>
      </correction> und Jackentaschen dreimal durchwühlt waren, musste sie zugeben, dass kein Kassenbon vorhanden war. Ein gefälliges Grinsen der Verkäuferin, ein <correction>
        <deletion>a</deletion>
      </correction> Anruf beim Sicherheitsdienst und schon saß <entity>Maria </entity><error>
        <errorType />

        <originalForm>ihm Hinteraum</originalForm>

        <targetForm>im Hinterraum</targetForm>
      </error> des Supermarktes und <correction>
        <deletion>n</deletion>
      </correction> wurde von einem von sich selbst <correction>
        <deletion><unreadable /></deletion>
      </correction> überzeugten, schwarz gekleideten Mann ausgefragt. <entity>Maria</entity>, die bekanntlich sehr <error>
        <errorType />

        <originalForm>wortgewand</originalForm>

        <targetForm>wortgewandt</targetForm>
      </error> ist überzeugte den netten Herrn sie zum Gemüseladen zu begleiten, um von der Verkäuferin ihren dortigen Einkauf versichert zu bekommen. So konnte <entity>Maria</entity> ihren Kopf wieder aus der Schlinge ziehen.... Aber diese Geschichte wird sie nicht so schnell vergessen, die Gute!                  </exercise>

    <exercise number="2" xml:space="preserve"><greeting>Hey <entity>Paula</entity></greeting>!<par />Seitdem wir beschlossen haben zusammen in den Urlaub zu fahren, mache ich mir Gedanken wohin wir fahren - l<overwrite>
        <under>i</under>

        <over>e</over>
      </overwrite>ider ohne Erfolg. Ich bin mir einfach nicht schlüssig ob ich lieber <correction>
        <deletion>in die Berge</deletion>
      </correction> einen Wanderurlaub in den Bergen, <correction>
        <deletion>mit</deletion>
      </correction> oder einen sonnigen Strandurlaub machen möchte. Du kennst mich ja - ich bin <error>
        <errorType />

        <originalForm>Entscheidungsunfähig</originalForm>

        <targetForm>entscheidungsunfähig</targetForm>
      </error>. An beiden Orten hat man super Bewegungs- und Entspannungsmöglich<hyphen>-</hyphen>keiten was die Entscheidung nicht leichter macht. In den Bergen hat man die Möglichkeit zu wandern, die frische Luft zu genießen, im Grünen zu faulenzen und das tolle Panorama zu genießen - dabei vitalisiert man auch noch seinen ganzen Körper.<par />Am Strand in der Sonne liegen und spüren wie der Körper Glückshormone <correction>
        <deletion>fre</deletion>
      </correction> produziert, dann ins Meer rennen um sich zu erfrischen - herrlich. Außerdem <correction>
        <deletion>hat</deletion>
      </correction> wollte ich schon immer einen Tauchkurs machen um die vielfältige Unterwasserwelt zu entdecken. Surfen oder Segeln wäre auch ein Reiz. <correction>
        <deletion>Den</deletion>
      </correction> Das weiche Gefühl des Sandes an den Füßen und entspann<overwrite>
        <under>t</under>

        <over>e</over>
      </overwrite>nde Musik in den Ohren, raus aus unserem eintönigen Alltag. Ich wünschte ich wäre jetzt dort!<par />Was meinst du? Wie sieht deine Entscheidung aus?<par /><closing>Bis demnächst,<par /><entity><over_capitalisation>
            <originalForm>LENA</originalForm>

            <targetForm>Lena</targetForm>
          </over_capitalisation></entity></closing>       </exercise>
  </body>
</kolipsi_document>
