<?xml version="1.0" encoding="utf-8"?>
<kolipsi_document xsi:schemaLocation="http://www.eurac.edu/kolipsi file:kolipsi.xsd"
                  xmlns="http://www.eurac.edu/kolipsi"
                  xmlns:xsi="http://www.w3.org/2001/XMLSchema-instance"
                  xmlns:xs="http://www.w3.org/2001/XMLSchema"
                  xmlns:ns="http://www.eurac.edu/kolipsi">
  <transcriber>Yella</transcriber>

  <author_id>M0220</author_id>

  <exam_type>Kolipsi</exam_type>

  <text_language>Deutsch</text_language>

  <body>
    <exercise number="1" xml:space="preserve"><greeting>Hey <entity>Gustav</entity></greeting>,<par />Was geht?<par />Ich war gestern mit <entity>Maria</entity> bei <entity>Akin</entity> im Obst-  und Gemüse<hyphen>-</hyphen>laden <sic>ne</sic>, die hat da Blumenkohl und Möhren gekauft. Eine Stunde später waren wir im Supermarkt und haben noch ein bisschen Wodka und Gin eingekauft für heute Abend <reduction>
        <reductionType rType="01 contraction" />

        <reducedForm>weisste</reducedForm>

        <unfoldedForm>weißt du</unfoldedForm>
      </reduction>. Und an der Kasse dachte die dumme Kassiererin, dass <entity>Maria</entity> Obst und Gemüse geklaut hat. Dann habe ich <entity>Akin</entity> angerufen, dann hat der auch gesagt, dass wir <gap>_</gap> Obst von seinem Laden hatten. <correction>
        <deletion>Ende gut alles gut</deletion>
      </correction> Die Kassiererin hat uns nicht geglaubt und rief die Polizei an. 10 Minuten später kamen die an und wollten uns eine Anzeige stellen, wegen Diebstahl <reduction>
        <reductionType rType="01 contraction" />

        <reducedForm>weisste</reducedForm>

        <unfoldedForm>weißt du</unfoldedForm>
      </reduction>. Dann ist <entity>Akin</entity> noch eingefallen, dass er Kameras im Laden hat. Wir sind zusammen mit den Polizisten hingefahren und haben die Kameraaufzeichnungen gezeigt. Jetzt war alles gut ja.<par /><closing>Haydi <entity>Gustav</entity> bis gleich.   </closing>    </exercise>

    <exercise number="2" xml:space="preserve"><greeting>Hey <entity>Olli</entity></greeting>:<par />Alles klar <error>
        <errorType />

        <originalForm>man</originalForm>

        <targetForm>Mann</targetForm>
      </error>? Wir wollten doch in den Ferien wegfliegen. Ich habe 2 Orte zur Auswahl. Der erste Ort ist die <entity>Eifel</entity> mit riesigen Bergen und schöner Natur. Der zweite Ort ist die <entity>Bahamas</entity> mit vielen schönen Mädels, <error>
        <errorType />

        <originalForm>hammer Cocktails</originalForm>

        <targetForm>Hammercocktails</targetForm>
      </error> und schönem Wetter. Ich glaub es ist klar, wo wir hinfliegen aber ich muss die Tickets übermorgen bestätigen. Also antworte schnell, ruf an oder ähhh.    </exercise>
  </body>
</kolipsi_document>
