<?xml version="1.0" encoding="utf-8"?>
<kolipsi_document xsi:schemaLocation="http://www.eurac.edu/kolipsi file:kolipsi.xsd"
                  xmlns="http://www.eurac.edu/kolipsi"
                  xmlns:xs="http://www.w3.org/2001/XMLSchema"
                  xmlns:ns="http://www.eurac.edu/kolipsi"
                  xmlns:xsi="http://www.w3.org/2001/XMLSchema-instance">
  <transcriber>Corinna</transcriber>

  <author_id>4349</author_id>

  <exam_type>Kolipsi</exam_type>

  <text_language>Deutsch</text_language>

  <body>
    <exercise number="1" xml:space="preserve"><correction>
        <deletion>Liebe Maria, ich habe eine sympatische Geschichte zu erzählen. Heute ist meine Freundin Maria zum Supermarkt gegangen. Sie hat Gemüse und Obst gekauft aber sie hat der vergessen. Dann</deletion>
      </correction> <par /><greeting>Liebe <entity>Maria</entity>,</greeting> <par />ich habe eine <error>
        <errorType />

        <originalForm>sympatische</originalForm>

        <targetForm>sympathische</targetForm>
      </error> Geschichte zu erzählen. He<palimpsest>u</palimpsest>te ist meine Freundin <entity>Maria</entity> <palimpsest>bei</palimpsest>m <palimpsest>Obs</palimpsest>thändler und zum Superm<palimpsest>a</palimpsest>kt gegangen. Wenn sie die Gemüse und Obst gekauft hat, ha<palimpsest>t</palimpsest> sie der Kassenzettel vergessen auf der <palimpsest>Kasse</palimpsest>. Dann ist sie im Supermarkt gegangen und an der Kasse gab es ein Problem. <palimpsest> </palimpsest> Die Frau, die an der Kasse st<palimpsest>an</palimpsest>d, dachte<palimpsest> </palimpsest> <correction>
        <insertion>dass</insertion>
      </correction> <entity>Maria</entity> eine Räuberin war, weil sie die Gemüse und <palimpsest>O</palimpsest>bst in der Tasche hatte. <entity>Maria</entity> könnte nicht geben der Kassenzettel zu <error>
        <errorType />

        <originalForm>Kassierin</originalForm>

        <targetForm>Kassiererin</targetForm>
      </error>, weil es beim Obsthändler war. Die <error>
        <errorType />

        <originalForm>Kassierin</originalForm>

        <targetForm>Kassiererin</targetForm>
      </error> hat die Polizei geruft. <entity>Maria</entity> hat gesagt, dass sie nicht eine Räuberin <palimpsest>w</palimpsest>ar, aber die Polizei dachte nicht es. Am Ende ist <entity>Maria</entity> zu Obsthändler gegangen und hat genommen ihrer Kasselzettel. Es war eine schlechte Tag für sie. <par /><closing><error>
          <errorType />

          <originalForm>Tschiuss</originalForm>

          <targetForm>Tschüss</targetForm>
        </error> <par /> <entity>Melissa</entity> </closing> </exercise>

    <exercise number="2" xml:space="preserve"><par />Liebe <entity>Morgan</entity>, <par />wie du <error>
        <errorType />

        <originalForm>weisst</originalForm>

        <targetForm>weißt</targetForm>
      </error>, ich wohne in <entity>Bozen</entity>, zwischen den Bergen. Ich liebe dieses Ort, weil so sauber ist und viele Grüne gibt es. Aber ich möchte ans Mee<overwrite>
        <under>e</under>

        <over>r</over>
      </overwrite> <palimpsest>pass</palimpsest>ieren mein<palimpsest> </palimpsest> Urlaub. Ich liebe das warme Klima und schwimmen. Denkst du es <palimpsest>wie</palimpsest> mir? Ans Meer gibt es mehr <correction>
        <insertion>junge</insertion>
      </correction> Leute und mehr Leben. Am Abend könn<overwrite>
        <under><unreadable /></under>

        <over>en</over>
      </overwrite> wir <palimpsest>zu</palimpsest> vielen <correction>
        <insertion><palimpsest>Pubs</palimpsest> </insertion>
      </correction>gehen. In<palimpsest> </palimpsest> die Berge gibt es mehr kalt und ist eines alleines Ort. Aber gibt es mehr Noten das Meer. Diese<palimpsest> </palimpsest> ist die erste Mal, dass wir zusammen d<palimpsest>er</palimpsest> Urlaub. Jetzt muss ich weggehen und so ich <error>
        <errorType />

        <originalForm>grüsse</originalForm>

        <targetForm>grüße</targetForm>
      </error> dir. <par /><closing>Küssen <par /> <entity>Melissa</entity> </closing> </exercise>
  </body>
</kolipsi_document>
