<?xml version="1.0" encoding="UTF-8"?>
<!DOCTYPE html PUBLIC "-//W3C//DTD XHTML 1.0 Transitional//EN" "http://www.w3.org/TR/xhtml1/DTD/xhtml1-transitional.dtd">
<root>
<body><page page_number="1" transcanno_page_id="152"><paragraph class="medium-paragraph" tagcode="1590074622299"><div>Eine <orth_error_id12 class="medium-orth_error_id12" orth_error_target="Haus" tagcode="1526740764634">House</orth_error_id12> <orth_error_id12 class="medium-orth_error_id12" orth_error_target="brennt" tagcode="1526740771666">Brennt</orth_error_id12>, eine Kind und eine</div><div><tran_unreadable_id17 class="medium-tran_unreadable_id17" tagcode="1527271821259">*onn</tran_unreadable_id17> <tran_word_deletion_id8 class="medium-tran_word_deletion_id8" tagcode="1526740818506" tran_word_deletion_target="_#_">komen</tran_word_deletion_id8> gehen in <orth_error_id12 class="medium-orth_error_id12" orth_error_target="Haus" tagcode="1526740826790">hous</orth_error_id12> <tran_ambiguous_id3 class="medium-tran_ambiguous_id3" tagcode="1526740849066" tran_alternative_1="end" tran_alternative_2="and">und</tran_ambiguous_id3> nehmen</div><div>alles von <orth_error_id12 class="medium-orth_error_id12" orth_error_target="das" tagcode="1526740901494"><tran_ambiguous_id3 class="medium-tran_ambiguous_id3" tagcode="1526740914786" tran_alternative_1="das" tran_alternative_2="">dos</tran_ambiguous_id3></orth_error_id12> <orth_error_id12 class="medium-orth_error_id12" orth_error_target="Haus" tagcode="1526740929242"><tran_ambiguous_id3 class="medium-tran_ambiguous_id3" tagcode="1526740953821" tran_alternative_1="haus" tran_alternative_2="">hous</tran_ambiguous_id3></orth_error_id12> <orth_error_id12 class="medium-orth_error_id12" orth_error_target="diese" tagcode="1526740997637">dise</orth_error_id12> <orth_error_id12 class="medium-orth_error_id12" orth_error_target="Kind" tagcode="1527271847854">kind</orth_error_id12> <tran_ambiguous_id3 class="medium-tran_ambiguous_id3" tagcode="1526741131208" tran_alternative_1="mint" tran_alternative_2="nint"><orth_error_id12 class="medium-orth_error_id12" orth_error_target="nimmt" tagcode="1526741137803">nimt</orth_error_id12></tran_ambiguous_id3></div><div>alles <tran_word_deletion_id8 class="medium-tran_word_deletion_id8" tagcode="1526741026394" tran_word_deletion_target="_#_">von</tran_word_deletion_id8> die <orth_error_id12 class="medium-orth_error_id12" orth_error_target="Schultasche" tagcode="1590074622298">Schultosche</orth_error_id12> und <tran_unreadable_id17 class="medium-tran_unreadable_id17" tagcode="1526741067185">d*</tran_unreadable_id17> <tran_unreadable_id17 class="medium-tran_unreadable_id17" tagcode="1526741072177">*oter</tran_unreadable_id17></div><div><orth_error_id12 class="medium-orth_error_id12" orth_error_target="nimmt" tagcode="1526741089430"><tran_ambiguous_id3 class="medium-tran_ambiguous_id3" tagcode="1526741149137" tran_alternative_1="mint" tran_alternative_2="nint">nimt</tran_ambiguous_id3></orth_error_id12> alle <tran_ambiguous_id3 class="medium-tran_ambiguous_id3" tagcode="1527271890191" tran_alternative_1="von" tran_alternative_2="">vor</tran_ambiguous_id3> das <orth_error_id12 class="medium-orth_error_id12" orth_error_target="Haus" tagcode="1526741170777">hous</orth_error_id12>.</div></paragraph></page></body>
</root>