<?xml version="1.0" encoding="UTF-8"?>
<kolipsi_II_document xmlns="http://www.eurac.edu/kolipsi_II"
                     xmlns:xsi="http://www.w3.org/2001/XMLSchema-instance"
                     xmlns:xs="http://www.w3.org/2001/XMLSchema"
                     xmlns:ns="http://www.eurac.edu/kolipsi_II"
                     xsi:schemaLocation="http://www.eurac.edu/kolipsi_II file:kolipsi_II.xsd">
  <transcriber>Anna</transcriber>

  <author_id>I14_COV31SER</author_id>

  <exam_type>Kolipsi II</exam_type>

  <text_language>Deutsch</text_language>

  <body>
      <exercise number="1" xml:space="preserve"><greeting>Hallo Serena</greeting><par/>wie geht's es dir? Mir geht es gut!<par/><correction>
        <deletion>Heute bin ich</deletion>
      </correction> Heute bin ich im Supermarkt gewesen wie die andere Tage und ich habe viele <error>
        <errorType/>

        <originalForm>Obst</originalForm>

        <targetForm>Obst-</targetForm>
      </error> und Gemüseladen eingekaufen. Ich muss im Supermarkt gehen alle Tage weil ich habe eine <error>
        <errorType/>

        <originalForm>größe</originalForm>

        <targetForm>große</targetForm>
      </error> Familie. Wie du weißt ich habe zwei Kinder Marta und Sara und jetzt sind sie größer geworden.<par/>Mir <error>
        <errorType/>

        <originalForm>gefählt</originalForm>

        <targetForm>gefällt</targetForm>
      </error> sehr im Supermarkt gehen und viele Sache <correction>
        <deletion>g</deletion>
      </correction> kaufen. Ich gehe immer alleine weil meine Kinder sind zu Schule. Heute bin ich im Supermarkt gewesen und ich habe viele Sache einkaufen weil am Abendessen habe ich meine Eltern <correction>
        <deletion>einladen.</deletion>
      </correction> eingeladen.<par/>Wenn ich in der Kassen bin habe ich weniger <error>
        <errorType/>

        <originalForm>gelde</originalForm>

        <targetForm>Gelde</targetForm>
      </error> zu kaufen alle Sache. So ich muss weniger Sache lassen </exercise>

    
  </body>
</kolipsi_II_document>