<?xml version="1.0" encoding="UTF-8"?>
<!DOCTYPE html PUBLIC "-//W3C//DTD XHTML 1.0 Transitional//EN" "http://www.w3.org/TR/xhtml1/DTD/xhtml1-transitional.dtd">
<root>
<body><page page_number="1" transcanno_page_id="1999"><paragraph class="medium-paragraph" tagcode="1555530323572"><div><tran_symbol_id32 class="medium-tran_symbol_id32" tagcode="1550045673291" tran_symbol_target="U+2192">--&amp;gt;</tran_symbol_id32> Nach meiner <tran_word_correction_id25 class="medium-tran_word_correction_id25" tagcode="1550045541918" tran_correction_original="M**nung">Meinung</tran_word_correction_id25> sollten sie auch Spanisch, Arabisch</div><div>Französisch, Deutsch, <tran_word_deletion_id8 class="medium-tran_word_deletion_id8" tagcode="1550045573420" tran_word_deletion_target="_#_">und</tran_word_deletion_id8> Englisch und Italienisch</div><div><tran_symbol_id32 class="medium-tran_symbol_id32" tagcode="1550045679590" tran_symbol_target="U+2192">--&amp;gt;</tran_symbol_id32> Weil Spanisch und Französisch wichtigen Sprachen <orth_error_id12 class="medium-orth_error_id12" orth_error_target="Europas" tagcode="1550045719963">Eropas</orth_error_id12> und</div><div><tran_word_correction_id25 class="medium-tran_word_correction_id25" tagcode="1550045757251" tran_correction_original="**h">ich</tran_word_correction_id25> möchte in Spanien und in Frankreich gehen, <tran_word_correction_id25 class="medium-tran_word_correction_id25" tagcode="1550045771168" tran_correction_original="a*er">aber</tran_word_correction_id25> auch</div><div><orth_error_id12 class="medium-orth_error_id12" orth_error_target="Arabisch" tagcode="1550045788265">arabisch</orth_error_id12> so könnten wir verstehen, wenn uns jemand etwas</div><div><orth_error_id12 class="medium-orth_error_id12" orth_error_target="Schlimmes" tagcode="1555530323571">schlimmes</orth_error_id12> sagt. <orth_error_id12 class="medium-orth_error_id12" orth_error_target="Englisch" tagcode="1550045813595">English</orth_error_id12> ist eine sehr wichtige <tran_word_correction_id25 class="medium-tran_word_correction_id25" tagcode="1550045841284" tran_correction_original="Sp*ach"><orth_error_id12 class="medium-orth_error_id12" orth_error_target="Sprache" tagcode="1550045852951">Sprach</orth_error_id12></tran_word_correction_id25>,</div><div>alle Staaten der Welt <orth_error_id12 class="medium-orth_error_id12" orth_error_target="können" tagcode="1550045871407">konnen</orth_error_id12> ein <tran_word_correction_id25 class="medium-tran_word_correction_id25" tagcode="1550045911185" tran_correction_original="bi**hen"><orth_error_id12 class="medium-orth_error_id12" orth_error_target="bisschen" tagcode="1550045919723">bischen</orth_error_id12></tran_word_correction_id25> Englisch und</div><div>also könnten wir mit ihnen reden. Deutsch verstehe</div><div>ich <tran_word_correction_id25 class="medium-tran_word_correction_id25" tagcode="1550046082263" tran_correction_original="sc**n">schon</tran_word_correction_id25>, <tran_word_correction_id25 class="medium-tran_word_correction_id25" tagcode="1550046089066" tran_correction_original="**h">ich</tran_word_correction_id25> mache aber zu vielen <orth_error_id12 class="medium-orth_error_id12" orth_error_target="Fehler" tagcode="1550046129778">Vehler</orth_error_id12>. Italienisch</div><div>kann <tran_word_correction_id25 class="medium-tran_word_correction_id25" tagcode="1550046141538" tran_correction_original="i*h">ich</tran_word_correction_id25> schon, aber wenn wir es lernen können auch die</div><div>Andere.</div></paragraph></page></body>
</root>